{
  "type": "FeatureCollection",
  "crs" : {
    "type" : "name",
    "properties" : {
      "name" : "EPSG:4326"
    }
  },
  "features": [
    {
      "type": "Feature",
      "properties": {
          "name": "Belledonne"
      },
      "geometry": {
        "type": "Point",
        "coordinates": [
          6.0376739501953125,
          45.2405691017678,
          2400
        ]
      }
    },
    {
      "type": "Feature",
      "properties": {
          "name": "Grenoble"
      },
      "geometry": {
        "type": "Point",
        "coordinates": [
          5.73211669921875,
          45.17719676486024,
          210
        ]
      }
    },
    {
      "type": "Feature",
      "properties": {
          "name": "Chartreuse Nord"
      },
      "geometry": {
        "type": "Point",
        "coordinates": [
          5.9456634521484375,
          45.45916739594383,
          800
        ]
      }
    },
    {
      "type": "Feature",
      "properties": {
          "name": "Saint Pierre de Chartreuse"
      },
      "geometry": {
        "type": "Point",
        "coordinates": [
          5.8124542236328125,
          45.343941498218996,
          900
        ]
      }
    },
    {
      "type": "Feature",
      "properties": {},
      "geometry": {
        "type": "LineString",
        "coordinates": [
          [
            5.73211669921875,
            45.17719676486024,
            210
          ],
          [
            5.75958251953125,
            45.20332826663052,
            213
          ],
          [
            5.810394287109375,
            45.213003555993964,
            216
          ],
          [
            5.83099365234375,
            45.236217535866025,
            219
          ],
          [
            5.881805419921875,
            45.25458854713424,
            222
          ],
          [
            5.91339111328125,
            45.289380486433295,
            225
          ],
          [
            5.92437744140625,
            45.30870012566985,
            228
          ],
          [
            5.955963134765625,
            45.333805815475024,
            231
          ],
          [
            5.997161865234375,
            45.41291242895992,
            234
          ],
          [
            6.002655029296875,
            45.454350939222046,
            237
          ],
          [
            6.02325439453125,
            45.487094732298374,
            240
          ],
          [
            6.013641357421874,
            45.508271755944975,
            243
          ],
          [
            5.988922119140625,
            45.51500822962093,
            246
          ],
          [
            5.964202880859375,
            45.53521281284293,
            249
          ],
          [
            5.9490966796875,
            45.56214096905606,
            252
          ],
          [
            5.907897949218749,
            45.57656146038471,
            255
          ]
        ]
      }
    }
  ]
}
